terminusgps_payments/__init__.py
terminusgps_payments/admin.py
terminusgps_payments/apps.py
terminusgps_payments/forms.py
terminusgps_payments/migrations/0001_initial.py
terminusgps_payments/migrations/0002_alter_customeraddressprofile_address_and_more.py
terminusgps_payments/migrations/__init__.py
terminusgps_payments/models/__init__.py
terminusgps_payments/models/address_profiles.py
terminusgps_payments/models/base.py
terminusgps_payments/models/customer_profiles.py
terminusgps_payments/models/payment_profiles.py
terminusgps_payments/models/subscriptions.py
terminusgps_payments-4.1.0.dist-info/METADATA
terminusgps_payments-4.1.0.dist-info/WHEEL
terminusgps_payments-4.1.0.dist-info/licenses/COPYING
terminusgps_payments-4.1.0.dist-info/RECORD
