Metadata-Version: 2.4
Name: terminusgps-payments
Version: 4.1.0
Summary: Add your description here
License-File: COPYING
Requires-Python: >=3.12
Requires-Dist: authorizenet>=1.1.6
Requires-Dist: django-encrypted-field>=1.0.5
Requires-Dist: django>=5.2.7
Requires-Dist: psycopg>=3.2.10
Requires-Dist: python-terminusgps>=50.2.1
